adaXT/__init__.py
adaXT/base_model.cp313-win32.pyd
adaXT/base_model.pyi
adaXT/parallel.py
adaXT/criteria/__init__.pxd
adaXT/criteria/__init__.py
adaXT/criteria/crit_helpers.cp313-win32.pyd
adaXT/criteria/crit_helpers.pxd
adaXT/criteria/criteria.cp313-win32.pyd
adaXT/criteria/criteria.pxd
adaXT/criteria/criteria.pyi
adaXT/decision_tree/__init__.pxd
adaXT/decision_tree/__init__.py
adaXT/decision_tree/_decision_tree.cp313-win32.pyd
adaXT/decision_tree/decision_tree.py
adaXT/decision_tree/nodes.cp313-win32.pyd
adaXT/decision_tree/nodes.pxd
adaXT/decision_tree/nodes.pyi
adaXT/decision_tree/splitter.cp313-win32.pyd
adaXT/decision_tree/splitter.pxd
adaXT/decision_tree/splitter.pyi
adaXT/decision_tree/tree_utils.py
adaXT/leaf_builder/__init__.pxd
adaXT/leaf_builder/__init__.py
adaXT/leaf_builder/leaf_builder.cp313-win32.pyd
adaXT/leaf_builder/leaf_builder.pxd
adaXT/leaf_builder/leaf_builder.pyi
adaXT/predictor/__init__.pxd
adaXT/predictor/__init__.py
adaXT/predictor/predictor.cp313-win32.pyd
adaXT/predictor/predictor.pxd
adaXT/predictor/predictor.pyi
adaXT/random_forest/__init__.py
adaXT/random_forest/random_forest.py
adaXT/utils/utils.cp313-win32.pyd
adaxt-1.5.1.dist-info/licenses/LICENSE
adaxt-1.5.1.dist-info/METADATA
adaxt-1.5.1.dist-info/WHEEL
adaxt-1.5.1.dist-info/top_level.txt
adaxt-1.5.1.dist-info/RECORD
