Metadata-Version: 2.4
Name: adaXT
Version: 1.5.1
Summary: A Python package for tree-based regression and classification
License: BSD-3-clause
Project-URL: Documentation, https://NiklasPfister.github.io/adaXT/
Project-URL: Source Code, https://github.com/NiklasPfister/adaXT
Classifier: Programming Language :: Python :: 3
Classifier: Intended Audience :: Science/Research
Classifier: Operating System :: OS Independent
Requires-Python: >=3.10
License-File: LICENSE
Requires-Dist: numpy>=1.25.0
Requires-Dist: matplotlib>=3.7.1
Requires-Dist: cython==3.1.0
Provides-Extra: test
Requires-Dist: scipy; extra == "test"
Requires-Dist: flake8; extra == "test"
Requires-Dist: pytest; extra == "test"
Dynamic: classifier
Dynamic: description
Dynamic: description-content-type
Dynamic: license
Dynamic: license-file
Dynamic: project-url
Dynamic: provides-extra
Dynamic: requires-dist
Dynamic: requires-python
Dynamic: summary
